lmautomation.py
mlmddr.py
ddr_lm-1.0.30.dist-info/LICENSE
ddr_lm-1.0.30.dist-info/METADATA
ddr_lm-1.0.30.dist-info/WHEEL
ddr_lm-1.0.30.dist-info/top_level.txt
ddr_lm-1.0.30.dist-info/RECORD
