Metadata-Version: 2.1
Name: ddr-lm
Version: 1.0.30
Summary: Distributed Device Reasoning (DDR) and Lazy Maestro integration
Home-page: https://wwwin-github.cisco.com/petervh/ddr-lm
Author: Peter Van Horne
Author-email: petervh@cisco.com
Classifier: Programming Language :: Python :: 3
Classifier: License :: OSI Approved :: MIT License
Classifier: Operating System :: OS Independent
Requires-Python: >=3.9
License-File: LICENSE
